{
  "0-100 km/h":3.9,
  "0-100 mph":9.8,
  "0-60 mph":3.7,
  "100-0 km/h":38.2,
  "60-0 mph":116.8,
  "60-100 mph":6.1,
  "BoundingBox":[
    [
      -0.816,
      -1.81,
      -0.388
    ],
    [
      1.04,
      2.194,
      1.527
    ]
  ],
  "Braking G":1.029,
  "Config Type":"Rally",
  "Configuration":"Rally2 EVO - Safari",
  "Description":"Gravel kit tuned for rough and challenging Rally Safari. The setup is equipped with soft springs and tuned down dampers, combined with higher ride height, bullbar and snorkel to survive the toughest Safari.",
  "Drivetrain":"AWD",
  "Fuel Type":"Gasoline",
  "Induction Type":"Turbo",
  "Off-Road Score":46,
  "Performance Class":"8",
  "Population":0,
  "Power":291,
  "PowerPeakRPM":"4950 - 6400",
  "Propulsion":"ICE",
  "Top Speed":55.379511861105,
  "Torque":435,
  "TorquePeakRPM":"3200 - 4750",
  "Transmission":"Sequential",
  "Value":180006,
  "Weight":1435,
  "Weight/Power":4.9312714776632,
  "Years":{
    "max":2022,
    "min":2019
  }
}